{
	"viewId": "ng-table",
	"cellSize": "md",
	"forceFit": true,
	"gridview": true,
	"headertitles": true,
	"datatype": "local",
	"sortorder": "asc",
	"sortFirstCol": false,
	"loadui": "disable",
	"rowNum": 100,
	"rowList": [20, 30, 50],
	"usePager": true,
	"useSmarterColumnWidths": false,
	"viewsortcols": [false, "horizontal", true],
	"maxWidgetColumns": 4,
	"frozenStaticCols": false,
	"x1HorizontalScroll": true,
	"useGroupedHeaders": true,
	"maxSort": 3,
	"maxFilter": "Infinity",
	"multiSort": true,
	"x1Filters": true,
	"sortOnHiddenColumns": true,
	"filterOnHiddenColumns": true,
	"showFilterSettings": true,
	"showSortSettings": true,
	"showColumnSettings": true,
	"sortable": true,
	"searchAsYouType": false,
	"totalRow": false,
	"autoresizeOnLoad": true,
	"showFilterSettings": false,
	"showSortSettings": false,
	"showColumnSettings": true,	
	"columns": [
		{
			"index": "id",
			"name": "id",
			"resourceName": "id",
			"width": 100,
			"displayOrder": 1,
			"sorttype": "number",
			"sortCriteria": {
				"sortOrder": 1,
				"sortDirection": "asc"
			},
			"filterCriteria": null,
			"hidden": false
		}, 
		{
			"index": "jobType",
			"name": "jobType",
			"resourceName": "jobType",
			"width": 100,
			"displayOrder": 2,
			"sortCriteria": null,
			"filterCriteria": {
				"filter": {
					"value": "ARRAY"
				},
				"filterOperator": "CONTAIN",
				"filterOrder": 2
			},			
			"hidden": false
		}, 
		{
			"index": "jobName",
			"name": "jobName",
			"resourceName": "jobName",
			"width": 100,
			"displayOrder": 3,
			"sorttype": "enum",
			"sortCriteria": null,
			"filterCriteria": null,
			"hidden": false
		},
		{
			"index": "jobStatus",
			"name": "jobStatus",
			"resourceName": "jobStatus",
			"width": 100,
			"displayOrder": 4,
			"sorttype": "text",
			"sortCriteria": null,
			"filterCriteria": null,
			"hidden": false
		}, 
		{
			"index": "appType",
			"name": "appType",
			"resourceName": "appType",
			"width": 100,
			"displayOrder": 5,
			"sorttype": "text",
			"sortCriteria": null,
			"filterCriteria": null,
			"hidden": false
		}, 
		{
			"index": "submitTime",
			"name": "submitTime",
			"resourceName": "submitTime",
			"width": 100,
			"displayOrder": 6,
			"sorttype": "text",
			"sortCriteria": null,
			"filterCriteria": null,
			"hidden": false
		},	
		{
			"index": "startTime",
			"name": "startTime",
			"resourceName": "startTime",
			"width": 100,
			"displayOrder": 7,
			"sorttype": "text",
			"sortCriteria": null,
			"filterCriteria": null,
			"hidden": false
		},
		{
			"index": "endTime",
			"name": "endTime",
			"resourceName": "endTime",
			"width": 100,
			"displayOrder": 8,
			"sorttype": "text",
			"sortCriteria": null,
			"filterCriteria": null,
			"hidden": false
		},
		{
			"index": "user",
			"name": "user",
			"resourceName": "user",
			"width": 100,
			"displayOrder": 9,
			"sorttype": "text",
			"sortCriteria": null,
			"filterCriteria": null,
			"hidden": false
		},		
		{
			"index": "jobNotification",
			"name": "jobNotification",
			"resourceName": "jobNotification",
			"width": 100,
			"displayOrder": 10,
			"sorttype": "text",
			"sortCriteria": null,
			"filterCriteria": null,
			"hidden": false
		},
		{
			"index": "path",
			"name": "path",
			"resourceName": "path",
			"width": 100,
			"displayOrder": 11,
			"sorttype": "text",
			"sortCriteria": null,
			"filterCriteria": null,
			"hidden": false
		},
		{
			"index": "description",
			"name": "description",
			"resourceName": "description",
			"width": 100,
			"displayOrder": 12,
			"sorttype": "text",
			"sortCriteria": null,
			"filterCriteria": null,
			"hidden": false
		},		
		{
			"index": "exitStatus",
			"name": "exitStatus",
			"resourceName": "exitStatus",
			"width": 100,
			"displayOrder": 13,
			"sorttype": "text",
			"sortCriteria": null,
			"filterCriteria": null,
			"hidden": false
		},	
		{
			"index": "priority",
			"name": "priority",
			"resourceName": "priority",
			"width": 100,
			"displayOrder": 14,
			"sorttype": "text",
			"sortCriteria": null,
			"filterCriteria": null,
			"hidden": false
		},		
		{
			"index": "fromHost",
			"name": "fromHost",
			"resourceName": "fromHost",
			"width": 100,
			"displayOrder": 15,
			"sorttype": "text",
			"sortCriteria": null,
			"filterCriteria": null,
			"hidden": false
		},
		{
			"index": "graphicJob",
			"name": "graphicJob",
			"resourceName": "graphicJob",
			"width": 100,
			"displayOrder": 16,
			"sorttype": "text",
			"sortCriteria": null,
			"filterCriteria": null,
			"hidden": false
		},	
		{
			"index": "queue",
			"name": "queue",
			"resourceName": "queue",
			"width": 100,
			"displayOrder": 17,
			"sorttype": "text",
			"sortCriteria": null,
			"filterCriteria": null,
			"hidden": false
		},
		{
			"index": "exHosts",
			"name": "exHosts",
			"resourceName": "exHosts",
			"width": 100,
			"displayOrder": 18,
			"sorttype": "text",
			"sortCriteria": null,
			"filterCriteria": null,
			"hidden": false
		},	
		{
			"index": "askedHosts",
			"name": "askedHosts",
			"resourceName": "askedHosts",
			"width": 100,
			"displayOrder": 19,
			"sorttype": "text",
			"sortCriteria": null,
			"filterCriteria": null,
			"hidden": false
		},
		{
			"index": "deleteTime",
			"name": "deleteTime",
			"resourceName": "deleteTime",
			"width": 100,
			"displayOrder": 20,
			"sorttype": "text",
			"sortCriteria": null,
			"filterCriteria": null,
			"hidden": false
		},
		{
			"index": "command",
			"name": "command",
			"resourceName": "command",
			"width": 100,
			"displayOrder": 21,
			"sorttype": "text",
			"sortCriteria": null,
			"filterCriteria": null,
			"hidden": false
		},
		{
			"index": "runTime",
			"name": "runTime",
			"resourceName": "runTime",
			"width": 100,
			"displayOrder": 22,
			"sorttype": "text",
			"sortCriteria": null,
			"filterCriteria": null,
			"hidden": false
		},
		{
			"index": "remainingTime",
			"name": "remainingTime",
			"resourceName": "remainingTime",
			"width": 100,
			"displayOrder": 23,
			"sorttype": "text",
			"sortCriteria": null,
			"filterCriteria": null,
			"hidden": false
		},
		{
			"index": "estimatedRunTime",
			"name": "estimatedRunTime",
			"resourceName": "estimatedRunTime",
			"width": 100,
			"displayOrder": 24,
			"sorttype": "text",
			"sortCriteria": null,
			"filterCriteria": null,
			"hidden": false
		},
		{
			"index": "mem",
			"name": "mem",
			"resourceName": "mem",
			"width": 100,
			"displayOrder": 25,
			"sorttype": "text",
			"sortCriteria": null,
			"filterCriteria": null,
			"hidden": false
		},	
		{
			"index": "swap",
			"name": "swap",
			"resourceName": "swap",
			"width": 100,
			"displayOrder": 26,
			"sorttype": "text",
			"sortCriteria": null,
			"filterCriteria": null,
			"hidden": false
		},	
		{
			"index": "nthreads",
			"name": "nthreads",
			"resourceName": "nthreads",
			"width": 100,
			"displayOrder": 27,
			"sorttype": "text",
			"sortCriteria": null,
			"filterCriteria": null,
			"hidden": false
		},	
		{
			"index": "pgid",
			"name": "pgid",
			"resourceName": "pgid",
			"width": 100,
			"displayOrder": 28,
			"sorttype": "text",
			"sortCriteria": null,
			"filterCriteria": null,
			"hidden": false
		},
		{
			"index": "pid",
			"name": "pid",
			"resourceName": "pid",
			"width": 100,
			"displayOrder": 28,
			"sorttype": "text",
			"sortCriteria": null,
			"filterCriteria": null,
			"hidden": false
		},		
		{
			"index": "infile",
			"name": "infile",
			"resourceName": "infile",
			"width": 100,
			"displayOrder": 29,
			"sorttype": "text",
			"sortCriteria": null,
			"filterCriteria": null,
			"hidden": false
		},
		{
			"index": "outfile",
			"name": "outfile",
			"resourceName": "outfile",
			"width": 100,
			"displayOrder": 30,
			"sorttype": "text",
			"sortCriteria": null,
			"filterCriteria": null,
			"hidden": false
		},
		{
			"index": "projectName",
			"name": "projectName",
			"resourceName": "projectName",
			"width": 100,
			"displayOrder": 31,
			"sorttype": "text",
			"sortCriteria": null,
			"filterCriteria": null,
			"hidden": false
		},			
		{
			"index": "cwd",
			"name": "cwd",
			"resourceName": "cwd",
			"width": 100,
			"displayOrder": 32,
			"sorttype": "text",
			"sortCriteria": null,
			"filterCriteria": null,
			"hidden": false
		},
		{
			"index": "execCwd",
			"name": "execCwd",
			"resourceName": "execCwd",
			"width": 100,
			"displayOrder": 33,
			"sorttype": "text",
			"sortCriteria": null,
			"filterCriteria": null,
			"hidden": false
		},
		{
			"index": "app",
			"name": "app",
			"resourceName": "app",
			"width": 100,
			"displayOrder": 34,
			"sorttype": "text",
			"sortCriteria": null,
			"filterCriteria": null,
			"hidden": false
		},
		{
			"index": "numProcessors",
			"name": "numProcessors",
			"resourceName": "numProcessors",
			"width": 100,
			"displayOrder": 35,
			"sorttype": "text",
			"sortCriteria": null,
			"filterCriteria": null,
			"hidden": false
		},	
		{
			"index": "exeHostClusterName",
			"name": "exeHostClusterName",
			"resourceName": "exeHostClusterName",
			"width": 100,
			"displayOrder": 36,
			"sorttype": "text",
			"sortCriteria": null,
			"filterCriteria": null,
			"hidden": false
		},
		{
			"index": "fromOwnFlowDefinition",
			"name": "fromOwnFlowDefinition",
			"resourceName": "fromOwnFlowDefinition",
			"width": 100,
			"displayOrder": 37,
			"sorttype": "text",
			"sortCriteria": null,
			"filterCriteria": null,
			"hidden": false
		}
	]
}
